redact_proxy/__init__.py
redact_proxy/anthropic_wrapper.py
redact_proxy/detector.py
redact_proxy/facilities.py
redact_proxy/gemini_wrapper.py
redact_proxy/models.py
redact_proxy/openai_wrapper.py
redact_proxy/patterns.py
redact_proxy/wordlists.py
redact_proxy/data/__init__.py
redact_proxy/data/cms_hospitals.txt
redact_proxy/data/cms_snf.txt
redact_proxy-0.1.5.dist-info/METADATA
redact_proxy-0.1.5.dist-info/WHEEL
redact_proxy-0.1.5.dist-info/licenses/NOTICE
redact_proxy-0.1.5.dist-info/RECORD
