Metadata-Version: 2.4
Name: redact-proxy
Version: 0.1.5
Summary: The ngrok for PHI. HIPAA-compliant wrappers for LLM APIs.
Project-URL: Homepage, https://redact.health
Project-URL: Product Page, https://www.redact.health/redact-proxy
Project-URL: Repository, https://github.com/cspergel/redact-proxy
Project-URL: Issues, https://github.com/cspergel/redact-proxy/issues
Author-email: Redact Health <hello@redact.health>
License-Expression: MIT
License-File: NOTICE
Keywords: anthropic,de-identification,gemini,healthcare,hipaa,llm,openai,phi,pii,privacy,proxy
Classifier: Development Status :: 4 - Beta
Classifier: Intended Audience :: Developers
Classifier: Intended Audience :: Healthcare Industry
Classifier: License :: OSI Approved :: MIT License
Classifier: Operating System :: OS Independent
Classifier: Programming Language :: Python :: 3
Classifier: Programming Language :: Python :: 3.9
Classifier: Programming Language :: Python :: 3.10
Classifier: Programming Language :: Python :: 3.11
Classifier: Programming Language :: Python :: 3.12
Classifier: Topic :: Scientific/Engineering :: Medical Science Apps.
Classifier: Topic :: Security
Classifier: Topic :: Text Processing
Requires-Python: >=3.9
Requires-Dist: openai>=1.0.0
Provides-Extra: accurate
Requires-Dist: torch>=2.0.0; extra == 'accurate'
Requires-Dist: transformers>=4.30.0; extra == 'accurate'
Provides-Extra: all
Requires-Dist: anthropic>=0.18.0; extra == 'all'
Requires-Dist: google-generativeai>=0.3.0; extra == 'all'
Requires-Dist: presidio-analyzer>=2.2.0; extra == 'all'
Requires-Dist: spacy>=3.0.0; extra == 'all'
Requires-Dist: torch>=2.0.0; extra == 'all'
Requires-Dist: transformers>=4.30.0; extra == 'all'
Provides-Extra: anthropic
Requires-Dist: anthropic>=0.18.0; extra == 'anthropic'
Provides-Extra: balanced
Requires-Dist: presidio-analyzer>=2.2.0; extra == 'balanced'
Requires-Dist: spacy>=3.0.0; extra == 'balanced'
Provides-Extra: dev
Requires-Dist: pytest-asyncio>=0.21.0; extra == 'dev'
Requires-Dist: pytest>=7.0.0; extra == 'dev'
Requires-Dist: ruff>=0.1.0; extra == 'dev'
Provides-Extra: gemini
Requires-Dist: google-generativeai>=0.3.0; extra == 'gemini'
